znfields/__init__.py
znfields-0.1.2.dist-info/LICENSE
znfields-0.1.2.dist-info/METADATA
znfields-0.1.2.dist-info/WHEEL
znfields-0.1.2.dist-info/RECORD
