Metadata-Version: 2.1
Name: znfields
Version: 0.1.2
Summary: Lazy evaluation of dataclass fields
License: Apache-2.0
Author: Fabian Zills
Author-email: fzills@icp.uni-stuttgart.de
Requires-Python: >=3.10,<4.0
Classifier: License :: OSI Approved :: Apache Software License
Classifier: Programming Language :: Python :: 3
Classifier: Programming Language :: Python :: 3.10
Classifier: Programming Language :: Python :: 3.11
Classifier: Programming Language :: Python :: 3.12
Classifier: Programming Language :: Python :: 3.13
